dev_template/__init__.py
dev_template/dev_template.py
dev_template/config/config.ini
dev_template/templates/.gitignore
dev_template/templates/README.md
dev_template/templates/pyproject.toml
dev_template/templates/requirements.txt
dev_template/templates/setup.py
dev_template/templates/src/__init__.py
dev_template/templates/src/main.py
dev_template/templates/tests/__init__.py
dev_template/templates/tests/test_main.py
dev_template-1.1.6.dist-info/METADATA
dev_template-1.1.6.dist-info/WHEEL
dev_template-1.1.6.dist-info/entry_points.txt
dev_template-1.1.6.dist-info/licenses/LICENSE
dev_template-1.1.6.dist-info/RECORD
