Metadata-Version: 2.3
Name: dev_template
Version: 1.1.6
Summary: A streamlined tool for quickly setting up Python project directories with simplicity and speed. Ideal for developers and hobbyists, dev_template offers interactive prompts, cross-platform compatibility, and robust configuration management to ensure a consistent project structure and efficient dependency management.
Project-URL: Homepage, https://github.com/http-kennedy/dev_template
Project-URL: Source, https://github.com/http-kennedy/dev_template
Project-URL: Tracker, https://github.com/http-kennedy/dev_template/issues
Project-URL: Documentation, https://github.com/http-kennedy/dev_template/blob/main/README.md
Author: Kennedy, D.
Author-email: "Kennedy, D." <kennedy@mylaptop.dev>
License: CC0-1.0
License-File: LICENSE
Keywords: automation,dependency management,development,hobbyist,project setup,project structure,python,quick start,template,tooling
Classifier: Development Status :: 3 - Alpha
Classifier: Intended Audience :: Developers
Classifier: Intended Audience :: System Administrators
Classifier: License :: CC0 1.0 Universal (CC0 1.0) Public Domain Dedication
Classifier: Natural Language :: English
Classifier: Operating System :: OS Independent
Classifier: Programming Language :: Python :: 3
Classifier: Programming Language :: Python :: 3.6
Classifier: Programming Language :: Python :: 3.7
Classifier: Programming Language :: Python :: 3.8
Classifier: Programming Language :: Python :: 3.9
Classifier: Programming Language :: Python :: 3.10
Classifier: Programming Language :: Python :: 3.11
Classifier: Topic :: Software Development
Classifier: Topic :: Software Development :: Build Tools
Classifier: Topic :: Utilities
Requires-Python: >=3.6
Requires-Dist: colorama==0.4.6
Requires-Dist: prompt-toolkit<3.1,>=3.0.36
Requires-Dist: pydantic==2.7.4
Requires-Dist: questionary==2.0.1
Requires-Dist: tqdm==4.66.4
Provides-Extra: tests
Requires-Dist: pytest; extra == 'tests'
